{"title":"Combined feed","url":"https://LIFECORD.github.io/careet/all.xml","elements":[{"title":"undefined (Careet ─ Contents ─ MZ 용어 사전)","contents":"‘실제 사진’의 줄임말","retrieved":1722798931469},{"title":"undefined (Careet ─ Contents ─ MZ 용어 사전)","contents":"가짜 계정. ‘Fake Instagram’의 줄임말.","retrieved":1722798931470},{"title":"undefined (Careet ─ Contents ─ MZ 용어 사전)","contents":"‘중요한 건 꺾이지 않는 마음’을 줄인 말. 최약체 팀이 롤드컵에서 우승한 사건을 다룬 기사 제목에서 유래한 MZ세대 유행어.","retrieved":1722798931471},{"title":"undefined (Careet ─ Contents ─ MZ 용어 사전)","contents":"각종 액세서리 부자재를 일컫는 말. Z세대는 보통 아이돌 포토 카드를 꾸밀 때 파츠를 활용함.","retrieved":1722798931472},{"title":"undefined (Careet ─ Contents ─ MZ 용어 사전)","contents":"국민 룰의 줄임말. 보편적으로 통용되는 규칙 혹은 유행이라는 뜻.","retrieved":1722798931473},{"title":"undefined (Careet ─ Contents ─ MZ 용어 사전)","contents":"홈페이지 마스터의 줄임말. 아이돌 팬 페이지를 운영하며, 고화질 카메라로 아이돌 스케줄 사진과 동영상을 찍는 팬을 의미함.","retrieved":1722798931475}]}