{"title":"Combined feed","url":"https://LIFECORD.github.io/careet/all.xml","elements":[{"title":"undefined (Careet ─ Contents ─ MZ 용어 사전)","contents":"‘대리 커스터마이징’의 줄임말. 대리로 남의 아바타를 디자인해주는 것을 뜻함.","retrieved":1716894875098},{"title":"undefined (Careet ─ Contents ─ MZ 용어 사전)","contents":"‘소소하지만 확실한 성취감’의 줄임말.","retrieved":1716894875100},{"title":"undefined (Careet ─ Contents ─ MZ 용어 사전)","contents":"개그우먼 ‘김민경’과 ‘유니버스’의 합성어. ‘하하버스’의 뒤를 잇는 세계관으로 ‘그냥 하면 다 잘하는데, 정작 본인은 모르는 채로 살아온 세계관’을 뜻함.","retrieved":1716894875101},{"title":"undefined (Careet ─ Contents ─ MZ 용어 사전)","contents":"실감나는 경험을 선호하고 소비함으로써, 내가 지금 이곳에 존재하고 있음을 실감하는 세대.","retrieved":1716894875102},{"title":"undefined (Careet ─ Contents ─ MZ 용어 사전)","contents":"일 잘하는 사람을 뜻하는 신조어","retrieved":1716894875103},{"title":"undefined (Careet ─ Contents ─ MZ 용어 사전)","contents":"특정 대상을 칭찬할 때 쓰이는 ‘OO 맛집이다’라는 표현이 변형된 버전. ex) “캐릿 트렌드 미슐랭이네”","retrieved":1716894875104}]}