{"title":"Combined feed","url":"https://LIFECORD.github.io/careet/all.xml","elements":[{"title":"undefined (Careet ─ Contents ─ MZ 용어 사전)","contents":"탑로더 꾸미기의 줄임말. 포토 카드 케이스를 꾸미는 걸 말함.","retrieved":1724152678527},{"title":"undefined (Careet ─ Contents ─ MZ 용어 사전)","contents":"음식에 대해 식견이 높거나, 맛있는 음식 조합을 잘 아는 사람들을 뜻하는 말","retrieved":1724152678529},{"title":"undefined (Careet ─ Contents ─ MZ 용어 사전)","contents":"‘서버 종료’ 또는 ‘서비스 종료’를 줄여 부르는 말.","retrieved":1724152678529},{"title":"undefined (Careet ─ Contents ─ MZ 용어 사전)","contents":"대화가 없는 고독한 채팅방과 달리, 대화도 하며 특정 연예인의 짤(이미지)도 공유하는 카카오톡 오픈 채팅방.","retrieved":1724152678529},{"title":"undefined (Careet ─ Contents ─ MZ 용어 사전)","contents":"밥 먹을 때 보는 유튜브 영상, 콘텐츠 등을 의미함.","retrieved":1724152678530},{"title":"undefined (Careet ─ Contents ─ MZ 용어 사전)","contents":"‘새롭고 놀랍다’란 뜻으로 신기하면서도 참신한 경우에 사용되는 신조어.","retrieved":1724152678531}]}