{"title":"Combined feed","url":"https://LIFECORD.github.io/careet/all.xml","elements":[{"title":"undefined (Careet ─ Contents ─ MZ 용어 사전)","contents":"‘블로그 챌린지’의 줄임말. 6월부터 12월까지 6개월간 진행되는 장기 프로젝트로 매주 지정된 카테고리에 한 건 이상의 일기를 작성해야 챌린지를 이어갈 수 있음.","retrieved":1718363710807},{"title":"undefined (Careet ─ Contents ─ MZ 용어 사전)","contents":"가짜 계정. ‘Fake Instagram’의 줄임말.","retrieved":1718363710808},{"title":"undefined (Careet ─ Contents ─ MZ 용어 사전)","contents":"신발 ‘크록스’를 장식하는 아이템. 각종 캐릭터 모양 등 알파세대와 Z세대의 트렌드를 반영한 형태가 많음.","retrieved":1718363710809},{"title":"undefined (Careet ─ Contents ─ MZ 용어 사전)","contents":"먹다 + 해시태그(#)의 합성어. 주로 아이돌 팬들이 자신이 좋아하는 가수에게 음식을 추천해주고 싶을 때 사용함. 아이돌마다 고유의 먹시태그가 있음.","retrieved":1718363710810},{"title":"undefined (Careet ─ Contents ─ MZ 용어 사전)","contents":"실제로 알지는 못하지만 온라인 상에서 자주 소식을 접해서 내적으로 친밀감이 쌓였다는 뜻.","retrieved":1718363710811},{"title":"undefined (Careet ─ Contents ─ MZ 용어 사전)","contents":"King +‘열받네’의 합성어. 기본적으로 열받는다는 의미지만, Z세대 사이에선 다양한 의미로 활용됨.","retrieved":1718363710812}]}