{"title":"Combined feed","url":"https://LIFECORD.github.io/careet/all.xml","elements":[{"title":"undefined (Careet ─ Contents ─ MZ 용어 사전)","contents":"연예인이 자신의 팬들에게 선물을 주는 행동 혹은 그 선물을 가르키는 말.","retrieved":1708794966482},{"title":"undefined (Careet ─ Contents ─ MZ 용어 사전)","contents":"‘콘셉트(concept)’와 ‘~하는 사람(-er)’의 합성어로, 자신만의 설정을 만들어 행동하는 사람을 일컫는 말.","retrieved":1708794966483},{"title":"undefined (Careet ─ Contents ─ MZ 용어 사전)","contents":"헤어 메이크업 코디를 합쳐 부르는 말","retrieved":1708794966484},{"title":"undefined (Careet ─ Contents ─ MZ 용어 사전)","contents":"너무 많은 정보, 굳이 알려주지 않아도 될 정보를 일컫는 말(Too Much Information).","retrieved":1708794966485},{"title":"undefined (Careet ─ Contents ─ MZ 용어 사전)","contents":"‘유교’와 ‘girl’의 합성어로, 보수적인 사람을 일컫는 말.","retrieved":1708794966487},{"title":"undefined (Careet ─ Contents ─ MZ 용어 사전)","contents":"‘프린팅박스’의 줄임말.","retrieved":1708794966488}]}