{"title":"Combined feed","url":"https://LIFECORD.github.io/careet/all.xml","elements":[{"title":"undefined (Careet ─ Contents ─ MZ 용어 사전)","contents":"‘콜렉트북’의 줄임말로, 연예인 포토카드를 모아두는 앨범을 뜻함","retrieved":1706710477561},{"title":"undefined (Careet ─ Contents ─ MZ 용어 사전)","contents":"덕질 용어에서 처음 시작된 단어로 깡은 깐다의 줄임말. 원하는 제품을 깐다는 말로 해석할 수 있다. 비슷한 단어로는 언박싱이 있다.","retrieved":1706710477561},{"title":"undefined (Careet ─ Contents ─ MZ 용어 사전)","contents":"‘마음에 상처가 났다’는 뜻 .","retrieved":1706710477562},{"title":"undefined (Careet ─ Contents ─ MZ 용어 사전)","contents":"휴대폰·아이패드 배경화면, 카카오톡 테마 등 디지털 환경에 적용해서 사용할 수 있는 템플릿. 실물 굿즈가 아닌 온라인에서 배포할 수 있다는 점이 특징.","retrieved":1706710477563},{"title":"undefined (Careet ─ Contents ─ MZ 용어 사전)","contents":"대화가 없는 고독한 채팅방과 달리, 대화도 하며 특정 연예인의 짤(이미지)도 공유하는 카카오톡 오픈 채팅방.","retrieved":1706710477564},{"title":"undefined (Careet ─ Contents ─ MZ 용어 사전)","contents":"사진 보정 앱. 포토샵처럼 세세한 조절도 가능하다. 이런 감성을 묶어 부르는 VSCO girl이란 말도 있음.","retrieved":1706710477565}]}