{"title":"Combined feed","url":"https://LIFECORD.github.io/careet/all.xml","elements":[{"title":"undefined (Careet ─ Contents ─ MZ 용어 사전)","contents":"‘극도로 호감’의 줄임말. 비슷한 의미의 표현으로는 ‘최애(=가장 사랑함)’가 있음.","retrieved":1732559348344},{"title":"undefined (Careet ─ Contents ─ MZ 용어 사전)","contents":"드라마 덕후의 줄임말.","retrieved":1732559348345},{"title":"undefined (Careet ─ Contents ─ MZ 용어 사전)","contents":"큰 난리가 일어났다는 뜻. 어떤 물건이 너무 인기가 많아서 구하지 못해 난리인 현상에 주로 쓰임.","retrieved":1732559348349},{"title":"undefined (Careet ─ Contents ─ MZ 용어 사전)","contents":"휴대폰·아이패드 배경화면, 카카오톡 테마 등 디지털 환경에 적용해서 사용할 수 있는 템플릿. 실물 굿즈가 아닌 온라인에서 배포할 수 있다는 점이 특징.","retrieved":1732559348349},{"title":"undefined (Careet ─ Contents ─ MZ 용어 사전)","contents":"유명인이 자신의 성명이나 초상을 상품 등의 선전에 이용하는 것을 허락하는 권리.","retrieved":1732559348349},{"title":"undefined (Careet ─ Contents ─ MZ 용어 사전)","contents":"(공식적으로 촬영된 것이 아닌) 팬이 직접 찍은 사진.","retrieved":1732559348349}]}