{"title":"Combined feed","url":"https://LIFECORD.github.io/careet/all.xml","elements":[{"title":"undefined (Careet ─ Contents ─ MZ 용어 사전)","contents":"‘언팔로우(Unfollow)’의 줄임말. 팔로우를 취소하여 더이상 게시물을 받아보지 않는다는 뜻.","retrieved":1722186997946},{"title":"undefined (Careet ─ Contents ─ MZ 용어 사전)","contents":"배트 플립(bat flip)의 한국식 표기. 일명 ‘빠따 던지기’의 줄임말. 타자가 홈런이 짐작되는 타격을 한 뒤, 야구 방망이를 던지는 행위를 말함.","retrieved":1722186997947},{"title":"undefined (Careet ─ Contents ─ MZ 용어 사전)","contents":"돈으로 혼쭐을 내주겠다는 뜻. 그만큼 많이 팔아주겠다는 긍정적인 의미로 사용됨.","retrieved":1722186997948},{"title":"undefined (Careet ─ Contents ─ MZ 용어 사전)","contents":"네이버가 제공하는 연예인 라이브 방송 서비스.","retrieved":1722186997949},{"title":"undefined (Careet ─ Contents ─ MZ 용어 사전)","contents":"2023년 유행하기 시작한 절약 방식. 하루 지출 0원을 목표로 소비하는 것을 뜻함.","retrieved":1722186997950},{"title":"undefined (Careet ─ Contents ─ MZ 용어 사전)","contents":"안면이 없다는 뜻의 ‘초면’과 ‘멘션을 합친 트위터 용어.","retrieved":1722186997952}]}