{"title":"Combined feed","url":"https://LIFECORD.github.io/careet/all.xml","elements":[{"title":"undefined (Careet ─ Contents ─ MZ 용어 사전)","contents":"로맨스 판타지 장르를 줄여서 부르는 말. 최근 인기있는 웹소설 장르 중 하나.","retrieved":1717597131569},{"title":"undefined (Careet ─ Contents ─ MZ 용어 사전)","contents":"‘병약하다’의 어근인 ‘병약’과 아름다움을 뜻하는 한자 ‘美’의 합성어.  ‘약하고 수척해 보여서 보호 본능을 자극하는 매력이 있다’는 뜻.","retrieved":1717597131570},{"title":"undefined (Careet ─ Contents ─ MZ 용어 사전)","contents":"‘취업 뽀개기’의 줄임말. 취업에 성공했을 때 ‘취뽀했다’라고 함.","retrieved":1717597131571},{"title":"undefined (Careet ─ Contents ─ MZ 용어 사전)","contents":"독서, 기록 등 텍스트 콘텐츠를 힙하다고 여기는 새로운 경향.","retrieved":1717597131572},{"title":"undefined (Careet ─ Contents ─ MZ 용어 사전)","contents":"'잘 안다', '잘 아는 사람'이라는 뜻의 신조어.","retrieved":1717597131573},{"title":"undefined (Careet ─ Contents ─ MZ 용어 사전)","contents":"‘텍스트 대치’의 줄임말. 스마트폰 특정 자판을 누르면 정해진 문구가 나오도록 설정해둔 기능을 뜻함. Z세대는 보통 이모티콘이 들어간 주접 문구를 텍대로 설정해두고 활용함.","retrieved":1717597131575}]}