{"title":"Combined feed","url":"https://LIFECORD.github.io/careet/all.xml","elements":[{"title":"undefined (Careet ─ Contents ─ MZ 용어 사전)","contents":"독립적인 의사결정을 할 수 있는 소규모 애자일 조직","retrieved":1724483780237},{"title":"undefined (Careet ─ Contents ─ MZ 용어 사전)","contents":"인스타그램에서 2021년 출시한 숏폼 서비스.","retrieved":1724483780238},{"title":"undefined (Careet ─ Contents ─ MZ 용어 사전)","contents":"폴라로이드 꾸미기, 포토카드를 폴라로이드 형태로 인쇄해서 꾸미는 것.","retrieved":1724483780239},{"title":"undefined (Careet ─ Contents ─ MZ 용어 사전)","contents":"[밈] 아이돌 그룹 ‘CIX’ 멤버가 ‘어여자(얼른 자)’라고 하면 팬들이 ‘어남자’라고 답하며 말장난한 것에서 유래. 2023년 말부터, 팬덤 내에서 소소하게 유행 중. (2024년 5월 기준)","retrieved":1724483780239},{"title":"undefined (Careet ─ Contents ─ MZ 용어 사전)","contents":"청소년의 온라인 게임 중독을 막기 위한 심야 게임 규제로, 만 16세 미만 청소년은 밤 12시부터 다음 날 오전 6시까지 온라인 게임에 접속할 수 없도록 하는 내용의 규제.","retrieved":1724483780241},{"title":"undefined (Careet ─ Contents ─ MZ 용어 사전)","contents":"차가운 도시 남자의 줄임말.","retrieved":1724483780242}]}