{"title":"Combined feed","url":"https://LIFECORD.github.io/careet/all.xml","elements":[{"title":"undefined (Careet ─ Contents ─ MZ 용어 사전)","contents":"외국에서 온 물건이나 문화가 한국의 특성을 반영해 변형된 것을 뜻함.","retrieved":1714417995922},{"title":"undefined (Careet ─ Contents ─ MZ 용어 사전)","contents":"'잘 안다', '잘 아는 사람'이라는 뜻의 신조어.","retrieved":1714417995924},{"title":"undefined (Careet ─ Contents ─ MZ 용어 사전)","contents":"실제론 친환경이 아닌데 친환경인 척 광고하는 것.","retrieved":1714417995925},{"title":"undefined (Careet ─ Contents ─ MZ 용어 사전)","contents":"서로 간의 궁합이나 호흡을 부르는 데 쓰이는 말. ‘chemistry’에서 유래.","retrieved":1714417995926},{"title":"undefined (Careet ─ Contents ─ MZ 용어 사전)","contents":"오픈채팅방의 Z세대식 줄임말. Z세대는 오픈채팅방을 커뮤니티처럼 이용함.","retrieved":1714417995927},{"title":"undefined (Careet ─ Contents ─ MZ 용어 사전)","contents":"‘진지한 대화’의 줄임말.","retrieved":1714417995928}]}