{"title":"Combined feed","url":"https://LIFECORD.github.io/careet/all.xml","elements":[{"title":"undefined (Careet ─ Contents ─ MZ 용어 사전)","contents":"2023년 유행하기 시작한 절약 방식. 하루 지출 0원을 목표로 소비하는 것을 뜻함.","retrieved":1721657901901},{"title":"undefined (Careet ─ Contents ─ MZ 용어 사전)","contents":"‘제페토 크루’를 줄여서 부르는 말로, 제페토를 함께 즐길 ‘파티원’을 뜻함.","retrieved":1721657901902},{"title":"undefined (Careet ─ Contents ─ MZ 용어 사전)","contents":"‘본래의 캐릭터’의 줄임말.","retrieved":1721657901904},{"title":"undefined (Careet ─ Contents ─ MZ 용어 사전)","contents":"덕질 용어에서 처음 시작된 단어로 깡은 깐다의 줄임말. 원하는 제품을 깐다는 말로 해석할 수 있다. 비슷한 단어로는 언박싱이 있다.","retrieved":1721657901905},{"title":"undefined (Careet ─ Contents ─ MZ 용어 사전)","contents":"셀프로 나의 캐릭터를 해석한다는 뜻으로, 스스로의 특징을 분석해 나의 이미지를 설정하는 것을 말함. MBTI 테스트가 대표적인 셀프캐해 콘텐츠.","retrieved":1721657901906},{"title":"undefined (Careet ─ Contents ─ MZ 용어 사전)","contents":"인스타그램에서 2021년 출시한 숏폼 서비스.","retrieved":1721657901907}]}