{"title":"Careet ─ Contents ─ MZ 용어 사전","url":"https://www.careet.net/Dictionary","favicon":"https://www.careet.net/content/images/favicon.ico","elements":[{"title":"코스프레","contents":"‘코스튬 플레이(costume play)’의 줄임말. 게임·만화 속 캐릭터로 분장하고, 그들과 비슷한 행동을 흉내내는 것을 뜻함. 일종의 퍼포먼스라고 볼 수 있음.","retrieved":1695709311495},{"title":"OO깡","contents":"덕질 용어에서 처음 시작된 단어로 깡은 깐다의 줄임말. 원하는 제품을 깐다는 말로 해석할 수 있다. 비슷한 단어로는 언박싱이 있다.","retrieved":1695709311495},{"title":"멍","contents":"불멍, 물멍, 숲멍 등 최근 MZ세대 사이에선 편안한 경관 앞에서 멍을 때리며 휴식을 취하는 것이 트렌드로 떠오름.","retrieved":1695709311495},{"title":"인싸","contents":"‘인사이더(insider)’를 줄인 한국식 영어 표현. 사람들과 잘 어울리며 발이 넓은 사람을 뜻함.","retrieved":1695709311497},{"title":"구독팟","contents":"‘구독 파티원’의 줄임말. 구독료를 1/N 내고 사용하기 위해 여러 명이서 구독 서비스를 신청하는 MZ세대 문화를 나타냄.","retrieved":1695709311499},{"title":"어드벤트 캘린더","contents":"12월 1일부터 24일까지 크리스마스를 기다리면서 하나씩 선물을 열어보는 형식의 달력.","retrieved":1695709311500}]}