{"title":"Careet ─ Contents ─ MZ 용어 사전","url":"https://www.careet.net/Dictionary","favicon":"https://www.careet.net/content/images/favicon.ico","elements":[{"title":"POV","contents":"시점이라는 뜻의 ‘Point of View’의 약어. 주로 틱톡에서 상황극을 부르는 말로 쓰임.","retrieved":1687799828434},{"title":"음식 예절샷","contents":"맛있는 음식을 먹을 때 포토카드를 들고 사진을 찍어 SNS에 공유하는 Z세대 온라인 문화를 부르는 말","retrieved":1687799828435},{"title":"박음질","contents":"인스타그램 스토리 게시물을 하루에 많이 올리는 일을 부르는 MZ세대 유행어. 하루에 올린 게시물 개수만큼 화면 상단에 점이 찍히는 것에서 유래.","retrieved":1687799828436},{"title":"엄카","contents":"‘엄마 카드’ 등 부모님의 카드를 부르는 말.","retrieved":1687799828438},{"title":"플미","contents":"‘프리미엄’의 줄임말. 주로 희소성있는 제품이 판매가보다 비싸게 거래될 때 ‘플미붙었다’고 표현함.","retrieved":1687799828439},{"title":"로판","contents":"로맨스 판타지 장르를 줄여서 부르는 말. 최근 인기있는 웹소설 장르 중 하나.","retrieved":1687799828440}]}