{"title":"Careet ─ Contents ─ MZ 용어 사전","url":"https://www.careet.net/Dictionary","favicon":"https://www.careet.net/content/images/favicon.ico","elements":[{"title":"달글","contents":"‘달리는 글’의 줄임말. 한 가지 주제가 정해지면 그 주제에 대해서만 얘기하는 글을 뜻함. 유사한 커뮤니티 문화로는 ‘불판’이 있음.","retrieved":1691471717318},{"title":"뽐뿌","contents":"무언가를 소비하고 싶은 충동을 부르는 온라인 유행어.","retrieved":1691471717320},{"title":"초멘","contents":"안면이 없다는 뜻의 ‘초면’과 ‘멘션을 합친 트위터 용어.","retrieved":1691471717322},{"title":"키자니아","contents":"어린이들이 직업을 체험할 수 있는 테마파크. 특정 직업을 생생하게 표현하거나 보여주는 콘텐츠를 볼 때 ‘어른들의 키자니아’라는 댓글이 많이 달림.","retrieved":1691471717324},{"title":"알계","contents":"트위터 계정 최초 생성 시 기본 프로필 사진인 알 그림을 프로필 사진으로 하고 있는 계정. 주로 본계를 숨기고 새로 계정을 만들어, 익명 뒤에 숨고 싶은 사람들이 이용함.","retrieved":1691471717325},{"title":"퍼블리시티권","contents":"유명인이 자신의 성명이나 초상을 상품 등의 선전에 이용하는 것을 허락하는 권리.","retrieved":1691471717327}]}