{"title":"Careet ─ Contents ─ MZ 용어 사전","url":"https://www.careet.net/Dictionary","favicon":"https://www.careet.net/content/images/favicon.ico","elements":[{"title":"좋댓구알","contents":"좋아요, 댓글, 구독, 알림설정의 줄임말","retrieved":1699521401719},{"title":"셀프 캐해","contents":"셀프로 나의 캐릭터를 해석한다는 뜻으로, 스스로의 특징을 분석해 나의 이미지를 설정하는 것을 말함. MBTI 테스트가 대표적인 셀프캐해 콘텐츠.","retrieved":1699521401722},{"title":"Z세대","contents":"1996년 이후 출생~2010년대 초반 출생자.","retrieved":1699521401725},{"title":"사이다 서사","contents":"기승전결을 빠르게 진행하는 서사 전개 형식. 독자가 보기에 답답하거나 전개가 느린 구간이 최소화되었음을 탄산음료의 시원함에 비유한 용어.","retrieved":1699521401728},{"title":"킹정","contents":"King +‘인정’의 합성어. 강한 인정을 의미함","retrieved":1699521401731},{"title":"파츠","contents":"각종 액세서리 부자재를 일컫는 말. Z세대는 보통 아이돌 포토 카드를 꾸밀 때 파츠를 활용함.","retrieved":1699521401733}]}