{"title":"Careet ─ Contents ─ MZ 용어 사전","url":"https://www.careet.net/Dictionary","favicon":"https://www.careet.net/content/images/favicon.ico","elements":[{"title":"덕력","contents":"덕후+力(힘)의 합성어로, 팬심이 깊은 사람에게 덕력이 높다는 표현을 씀.","retrieved":1647549253308},{"title":"공구","contents":"공동구매의 줄임말. 유튜버나 인플루언서가 기성 브랜드 제품을 홍보하고, 공동구매 방식으로 판매까지 유도하는 마케팅 수단.","retrieved":1647549253309},{"title":"총공","contents":"'총 공격'의 줄임말. 팬들의 단체 행동.","retrieved":1647549253311},{"title":"생정","contents":"생활 정보의 줄임말.","retrieved":1647549253312},{"title":"짠메랑","contents":"‘부메랑(gif 형식으로 사진을 찍어주는 필터)’기능을 활용해 술자리에서 건배하는 모습을 촬영하는 것.","retrieved":1647549253315},{"title":"잘알","contents":"'잘 안다', '잘 아는 사람'이라는 뜻의 신조어.","retrieved":1647549253316}]}