{"title":"Careet ─ Contents ─ MZ 용어 사전","url":"https://www.careet.net/Dictionary","favicon":"https://www.careet.net/content/images/favicon.ico","elements":[{"title":"교복템","contents":"마치 교복처럼 자주 입는(쓰는) 물건이라는 뜻.","retrieved":1649615067119},{"title":"머글","contents":"덕후가 아닌 일반인을 이르는 말. 영화 &lt;해리 포터&gt; 시리즈에서 마법사들이 일반인을 부르는 용어에서 비롯됨.","retrieved":1649615067120},{"title":"캐해석","contents":"캐릭터 해석의 줄임말. 특정 인물을 분석해 나름의 이미지를 설정하는 일을 의미함.","retrieved":1649615067121},{"title":"엄빠","contents":"엄마 아빠를 함께 일컫는 말.","retrieved":1649615067122},{"title":"포토 카드","contents":"아이돌 멤버의 사진으로 만든 카드로, 주로 앨범 당 한 장씩 들어있는 굿즈. 줄여서 ‘포카’라고 부름.","retrieved":1649615067123},{"title":"코끝모","contents":"코로나 끝나면 모이자를 줄인 신조어.","retrieved":1649615067124}]}