{"title":"Careet ─ Contents ─ MZ 용어 사전","url":"https://www.careet.net/Dictionary","favicon":"https://www.careet.net/content/images/favicon.ico","elements":[{"contents":"1981년~1996년에 출생한 세대를 가리키는 말. 대학내일20대연구소에선 심리적, 사회적 동질성을 고려해 1989년 이전 출생자는 전기 밀레니얼, 1989년 출생자부터는 후기 밀레니얼로 구분하고 있음.","retrieved":1718201907735},{"contents":"야구 갤러리+훈민정음의 합성어. 디시인사이드 야구 갤러리에서 만든 드립으로 원래 글자를 모양이 비슷한 다른 글자로 대체해 표기하는 방식. (ex. 멍멍이 → 댕댕이)","retrieved":1718201907736},{"contents":"위장 꾸미기. 맛있는 식사를 하는 것을 꾸미기에 빗대어 부르는 말.","retrieved":1718201907738},{"contents":"사진 보정 앱. 포토샵처럼 세세한 조절도 가능하다. 이런 감성을 묶어 부르는 VSCO girl이란 말도 있음.","retrieved":1718201907739},{"contents":"‘캘린더’와 ‘박제’의 줄임말. 중요한 일정을 캘린더에 저장해둔다는 뜻임.","retrieved":1718201907740},{"contents":"‘귀여워’를 초성만으로 표현한 단어.","retrieved":1718201907741}]}