{"title":"Careet ─ Contents ─ MZ 용어 사전","url":"https://www.careet.net/Dictionary","favicon":"https://www.careet.net/content/images/favicon.ico","elements":[{"title":"실사","contents":"실세 사진의 줄임말","retrieved":1650792067759},{"title":"생정","contents":"생활 정보의 줄임말.","retrieved":1650792067763},{"title":"맛집","contents":"‘이 집 잘한다’는 칭찬의 표현. ‘엔딩 맛집’, ‘케미(합) 맛집’ 등 다양한 단어 뒤에 붙임.","retrieved":1650792067763},{"title":"본캐","contents":"‘본래의 캐릭터’의 줄임말.","retrieved":1650792067764},{"title":"트시피","contents":"트위터+레시피를 합친 말. 트위터에서 유행하는 레시피를 뜻함.","retrieved":1650792067766},{"title":"알못","contents":"어떤 분야에 대해 잘 알지 못하는 사람을 부르는 말↔잘알","retrieved":1650792067768}]}