{"title":"Careet ─ Contents ─ MZ 용어 사전","url":"https://www.careet.net/Dictionary","favicon":"https://www.careet.net/content/images/favicon.ico","elements":[{"title":"굿즈","contents":"원래 연예인과 관련된 사진, 포토카드, 응원봉 등의 제품을 뜻했으나, 최근엔 ‘한정판으로 출시되는 매력적인 아이템’을 통칭하는 단어로 자리잡음.","retrieved":1685096304245},{"title":"홈술","contents":"집에서 술을 마시는 것. 코로나19 이후 증가한 트렌드.","retrieved":1685096304249},{"title":"헬시플레저","contents":"‘건강하다(Healthy)’와 ‘기쁨(Pleasure)’의 합성어. 건강관리에 즐거움을 부여해 지속가능한 건강관리를 추구하는 것을 의미함.","retrieved":1685096304251},{"title":"구독계","contents":"아무 말도 걸지 않고 그냥 상대방을 팔로해서 상대방이 쓰는 글을 보거나 리트윗만 하기 위해 이용하는 계정.","retrieved":1685096304252},{"title":"섭종","contents":"‘서버 종료’ 또는 ‘서비스 종료’를 줄여 부르는 말.","retrieved":1685096304254},{"title":"취준","contents":"‘취업 준비’의 줄임말.","retrieved":1685096304259}]}