{"title":"Careet ─ Contents ─ MZ 용어 사전","url":"https://www.careet.net/Dictionary","favicon":"https://www.careet.net/content/images/favicon.ico","elements":[{"title":"처돌이","contents":"치킨 브랜드 ‘처갓집’의 마스코트 ‘처돌이’에서 유래한 말. 특정 대상을 매우 좋아한다는 뜻.","retrieved":1680642911618},{"title":"병약미","contents":"‘병약하다’의 어근인 ‘병약’과 아름다움을 뜻하는 한자 ‘美’의 합성어.  ‘약하고 수척해 보여서 보호 본능을 자극하는 매력이 있다’는 뜻.","retrieved":1680642911618},{"title":"공구","contents":"공동구매의 줄임말. 유튜버나 인플루언서가 기성 브랜드 제품을 홍보하고, 공동구매 방식으로 판매까지 유도하는 마케팅 수단.","retrieved":1680642911619},{"title":"파티원","contents":"게임 용어로 함께 퀘스트를 깨러 갈 팀원이라는 의미.","retrieved":1680642911621},{"title":"부캐","contents":"원래 캐릭터(‘본캐’)가 아닌 또 다른 캐릭터. 온라인 게임에서 유래한 말.","retrieved":1680642911631},{"title":"긱 이코노미","contents":"Gig Economy. 기업들이 필요에 따라 단기 계약직이나 임시직으로 인력을 충원하고 그 대가를 지불하는 형태의 경제.","retrieved":1680642911631}]}