{"title":"Careet ─ Contents ─ MZ 용어 사전","url":"https://www.careet.net/Dictionary","favicon":"https://www.careet.net/content/images/favicon.ico","elements":[{"title":"알티스타","contents":"트윗의 리트윗(공유) 수가 1,000 단위를 넘어가며 화제가 되는 경우, 해당 트윗을 올린 트위터리안을 부르는 말.","retrieved":1676744531390},{"title":"컨셉러","contents":"‘콘셉트(concept)’와 ‘~하는 사람(-er)’의 합성어로, 자신만의 설정을 만들어 행동하는 사람을 일컫는 말.","retrieved":1676744531391},{"title":"초멘","contents":"안면이 없다는 뜻의 ‘초면’과 ‘멘션을 합친 트위터 용어.","retrieved":1676744531392},{"title":"엄빠","contents":"엄마 아빠를 함께 일컫는 말.","retrieved":1676744531393},{"title":"뉴노멀(New normal)","contents":"상황 변화에 따라 과거의 표준이 더 이상 통하지 않고 새로운 가치 표준이 세상 변화를 주도하는 상태.","retrieved":1676744531394},{"title":"팡인","contents":"‘광인’을 야민정음 방식으로 표기한 것. 특정 일에 미친듯이 몰두하는 사람을 지칭함.","retrieved":1676744531395}]}