{"title":"Careet ─ Contents ─ MZ 용어 사전","url":"https://www.careet.net/Dictionary","favicon":"https://www.careet.net/content/images/favicon.ico","elements":[{"contents":"‘입을 틀어 막다’의 줄임말. 주로 감정이 복받쳐 오를 때 사용함.","retrieved":1714050886930},{"contents":"PC 환경을 온라인에 구축해 어디서든 접속할 수 있게 하는 서비스.","retrieved":1714050886930},{"contents":"인터넷 소설의 줄임말.","retrieved":1714050886935},{"contents":"액체 괴물의 줄임말. 알파 세대에게 인기 있는 장난감인 ‘슬라임’을 지칭하는 용어이다.","retrieved":1714050886936},{"contents":"트위치 스트리머 ‘우왁굳’이 기획한 버추얼 아이돌","retrieved":1714050886936},{"contents":"King +‘열받네’의 합성어. 기본적으로 열받는다는 의미지만, Z세대 사이에선 다양한 의미로 활용됨.","retrieved":1714050886937}]}