{"title":"Careet ─ Contents ─ MZ 용어 사전","url":"https://www.careet.net/Dictionary","favicon":"https://www.careet.net/content/images/favicon.ico","elements":[{"title":"국그릇핑크퐁","contents":"웃음 소리를 나타낸 유행어 ‘ㅋㅋ루삥뽕’을 변형해서 쓰는 말.","retrieved":1698433931353},{"title":"팔이피플","contents":"팔이+people의 합성어로, SNS나 쇼핑몰에서 물건을 판매하는 사람들을 지칭하는 말.","retrieved":1698433931355},{"title":"삼현슼엘","contents":"국내 굴지의 대기업인 삼성, 현대, SK, LG를 통칭하는 말. MZ세대 취업 준비생들이 입사하고 싶어하는 꿈의 직장으로 꼽히는 기업들.","retrieved":1698433931362},{"title":"넘사벽","contents":"넘을 수 없는 4차원의 벽의 줄임말. 대상과 거리감이 많이 느껴질 때 주로 사용함.","retrieved":1698433931365},{"title":"펀슈머","contents":"‘Fun(재미)’과 ‘Consumer(소비자)’의 합성어로, 소비 과정에서 재미를 추구하는 소비자를 일컫는 말.","retrieved":1698433931367},{"title":"겟레디윗미","contents":"쌩얼 상태에서 메이크업을 완성하는 과정을 보여주는 콘텐츠. ‘Get Ready With Me(=나랑 같이 준비하자)’를 그대로 발음한 용어로, 줄여서 ‘GRWM’로도 쓰임.","retrieved":1698433931372}]}