{"title":"Careet ─ Contents ─ MZ 용어 사전","url":"https://www.careet.net/Dictionary","favicon":"https://www.careet.net/content/images/favicon.ico","elements":[{"contents":"트위터에서 다른 사람의 트윗 위에 자신의 의견을 덧붙여서 공유하는 기능.","retrieved":1727605201731},{"contents":"‘프린팅박스’의 줄임말.","retrieved":1727605201734},{"contents":"‘유교’와 ‘girl’의 합성어로, 보수적인 사람을 일컫는 말.","retrieved":1727605201734},{"contents":"Employee+Influencer. 직원으로서 기업의 브랜딩과 이미지에 영향력을 미치는 존재.","retrieved":1727605201734},{"contents":"SNS 내에서 자신의 일상을 감성 사진과 함께 올리는 계정을 일컫는 말","retrieved":1727605201735},{"contents":"엄청나게 버티다라는 뜻.","retrieved":1727605201736}]}