{"title":"Careet ─ Contents ─ MZ 용어 사전","url":"https://www.careet.net/Dictionary","favicon":"https://www.careet.net/content/images/favicon.ico","elements":[{"title":"실사","contents":"‘실제 사진’의 줄임말","retrieved":1697829252281},{"title":"광클","contents":"‘狂+click’의 줄임말. 아주 빠른 속도로 클릭하는 것을 의미함.","retrieved":1697829252282},{"title":"금손","contents":"손재주가 좋은 사람을 일컫는 말. 반대말은 똥손.","retrieved":1697829252282},{"title":"내적 친밀감","contents":"실제로 알지는 못하지만 온라인 상에서 자주 소식을 접해서 내적으로 친밀감이 쌓였다는 뜻.","retrieved":1697829252286},{"title":"게이미피케이션(Gamification)","contents":"게임적 사고와 게임 기법을 활용해 사용자를 몰입시키는 기법.","retrieved":1697829252290},{"title":"쿠키","contents":"네이버 웹툰에서 유료 결제를 할 수 있는 화폐. ‘유료 결제 한다’라는 뜻으로 ‘쿠키 굽는다’라는 표현을 씀.","retrieved":1697829252296}]}