{"title":"Careet ─ Contents ─ MZ 용어 사전","url":"https://www.careet.net/Dictionary","favicon":"https://www.careet.net/content/images/favicon.ico","elements":[{"title":"입덕","contents":"入(들어갈 입) + 덕질의 합성어. ‘어떤 포인트에 반해서 덕질을 시작하게 되다’라는 뜻.","retrieved":1705245381353},{"title":"쿠키","contents":"네이버 웹툰에서 유료 결제를 할 수 있는 화폐. ‘유료 결제 한다’라는 뜻으로 ‘쿠키 굽는다’라는 표현을 씀.","retrieved":1705245381355},{"title":"스밍","contents":"스트리밍의 줄임말. 아이돌 팬들이 음원 사이트에서 응원하는 가수의 노래를 차트 1위로 만들어주기 위해 반복해서 듣는 것을 ‘스밍 돌린다’고 표현함.","retrieved":1705245381356},{"title":"프박","contents":"‘프린팅박스’의 줄임말.","retrieved":1705245381357},{"title":"솜뭉치","contents":"MZ세대가 ‘인형’을 부르는 애칭.","retrieved":1705245381359},{"title":"홈트","contents":"‘홈 트레이닝’의 줄임말. 집에서 운동하는 것을 뜻함.","retrieved":1705245381361}]}