{"title":"Careet ─ Contents ─ MZ 용어 사전","url":"https://www.careet.net/Dictionary","favicon":"https://www.careet.net/content/images/favicon.ico","elements":[{"title":"블친","contents":"블로그 친구의 줄임말.","retrieved":1702034064252},{"title":"어쩔티비","contents":"알파 세대 유행어. ‘어쩌라고, TV나 봐’라는 의미로 추정됨.","retrieved":1702034064253},{"title":"래플","contents":"당첨자에게 한정판 상품을 구매할 권리를 주는 판매 방식. 이 방식을 활용하는 브랜드로는 대표적으로 나이키가 있음.","retrieved":1702034064254},{"title":"상플","contents":"‘상상 플레이’의 줄임말. MZ세대가 썰을 풀고 노는 문화를 칭하는 말.","retrieved":1702034064255},{"title":"글 리젠","contents":"글+리젠(regen)의 합성어. 게시판 등에 새로운 글이 자주 올라올 때 ‘글리젠이 빠르다’라고 표현함.","retrieved":1702034064256},{"title":"밖순이","contents":"집순이의 반대말로, 밖에서 노는 걸 좋아하는 사람을 일컫는 말.","retrieved":1702034064258}]}