{"title":"Careet ─ Contents ─ MZ 용어 사전","url":"https://www.careet.net/Dictionary","favicon":"https://www.careet.net/content/images/favicon.ico","elements":[{"title":"킹정","contents":"King +‘인정’의 합성어. 강한 인정을 의미함","retrieved":1650198824494},{"title":"비건","contents":"원래는 채식주의 중에서도 가장 엄격한 단계를 뜻하는 단어지만, 요즘은 철학적인 이유로 동물성 식품을 섭취하지 않는 사람들을 통칭해 ‘비건’이라고 부르는 경우가 많음.","retrieved":1650198824498},{"title":"에타","contents":"학교 인증을 거친 재학생들만 이용할 수 있는 익명 커뮤니티 플랫폼 ‘에브리타임’의 줄임말. 과거 학교 커뮤니티와 비슷한 기능을 함.","retrieved":1650198824500},{"title":"OTT","contents":"‘Over The Top’의 줄임말로 넷플릭스, 티빙, 웨이브 등의 온라인 동영상 서비스를 일컬음.","retrieved":1650198824501},{"title":"초멘","contents":"안면이 없다는 뜻의 ‘초면’과 ‘멘션을 합친 트위터 용어.","retrieved":1650198824501},{"title":"크루얼티 프리","contents":"‘학대(cruelty)가 없다(free)’는 의미로, 동물 실험을 하지 않거나 동물 유래 원료를 사용하지 않은 제품을 뜻함.","retrieved":1650198824503}]}