{"title":"Careet ─ Contents ─ MZ 용어 사전","url":"https://www.careet.net/Dictionary","favicon":"https://www.careet.net/content/images/favicon.ico","elements":[{"title":"자컨","contents":"‘자체 제작 컨텐츠’의 줄임말. 방송사가 아닌 K-POP 기획사가 직접 만든 소속 아이돌의 리얼리티 영상을 말함.","retrieved":1650378069091},{"title":"로판","contents":"로맨스 판타지 장르를 줄여서 부르는 말. 최근 인기있는 웹소설 장르 중 하나.","retrieved":1650378069096},{"title":"린스타","contents":"진짜 계정. ‘Real Instagram’의 줄임말.","retrieved":1650378069098},{"title":"헤메코","contents":"헤어 메이크업 코디를 합쳐 부르는 말","retrieved":1650378069099},{"title":"읽페","contents":"‘페이스북 스토리 읽으면 페메(페북 메신저) 보낸다’의 줄임말.","retrieved":1650378069099},{"title":"OO깡","contents":"덕질 용어에서 처음 시작된 단어로 깡은 깐다의 줄임말. 원하는 제품을 깐다는 말로 해석할 수 있다. 비슷한 단어로는 언박싱이 있다.","retrieved":1650378069100}]}