{"title":"Careet ─ Contents ─ MZ 용어 사전","url":"https://www.careet.net/Dictionary","favicon":"https://www.careet.net/content/images/favicon.ico","elements":[{"title":"처돌이","contents":"치킨 브랜드 ‘처갓집’의 마스코트 ‘처돌이’에서 유래한 말. 특정 대상을 매우 좋아한다는 뜻.","retrieved":1644287612610},{"title":"가심비","contents":"가격 대비 심리적 만족을 추구하는 소비 트렌드↔가성비","retrieved":1644287612612},{"title":"빛삭","contents":"‘빛의 속도로 삭제한다’의 줄임말로 인터넷상에 올린 게시물을 매우 빠르게 지운다는 의미.","retrieved":1644287612613},{"title":"커미션(commission)","contents":"보수를 받고 어떤 일을 처리해주는 행위. 주로 돈을 받고 원하는 콘텐츠(그림, 글)를 제작해줄 때 사용하는 말.","retrieved":1644287612614},{"title":"자컨","contents":"‘자체 제작 컨텐츠’의 줄임말. 방송사가 아닌 K-POP 기획사가 직접 만든 소속 아이돌의 리얼리티 영상을 말함.","retrieved":1644287612615},{"title":"코끝모","contents":"코로나 끝나면 모이자를 줄인 신조어.","retrieved":1644287612616}]}