{"title":"Careet ─ Contents ─ MZ 용어 사전","url":"https://www.careet.net/Dictionary","favicon":"https://www.careet.net/content/images/favicon.ico","elements":[{"title":"탑로더","contents":"위로 뚫려있는 입구로 사진이나 카드를 넣어 보관할 수 있는 플라스틱 재질의 보관함","retrieved":1682162050669},{"title":"고독한 채팅방","contents":"대화 없이 특정 연예인의 짤(이미지)만 공유하는 카카오톡 오픈 채팅방","retrieved":1682162050678},{"title":"무배","contents":"무료배송의 줄임말.","retrieved":1682162050678},{"title":"모먼트","contents":"‘순간’을 뜻하는 영어 단어인 ‘moment’를 그대로 발음한 말. 특정한 모습이나 행동을 보여주는 순간들을 강조할 때 사용함. [용례] ‘OO적 모먼트’","retrieved":1682162050678},{"title":"타래","contents":"트위터 기능 중 하나. 답변을 달며 묶음 트윗을 할 수 있음. 주로 긴 정보를 전달할 때 쓰임.","retrieved":1682162050687},{"title":"혼코노","contents":"‘혼자서 코인 노래방 가는 사람(or 행위)’의 줄임말.","retrieved":1682162050687}]}