{"title":"Careet ─ Contents ─ MZ 용어 사전","url":"https://www.careet.net/Dictionary","favicon":"https://www.careet.net/content/images/favicon.ico","elements":[{"contents":"치킨 브랜드 ‘처갓집’의 마스코트 ‘처돌이’에서 유래한 말. 특정 대상을 매우 좋아한다는 뜻.","retrieved":1706685358341},{"contents":"‘인기 급상승 동영상’의 줄임말. 유튜브에서 단시간에 높은 조회 수를 기록하고, 화제가 된 영상을 일컬음.","retrieved":1706685358342},{"contents":"‘답은 정해져 있고 너는 대답만 하면 돼’의 줄임말.","retrieved":1706685358343},{"contents":"웃음 소리를 나타낸 유행어 ‘ㅋㅋ루삥뽕’을 변형해서 쓰는 말.","retrieved":1706685358344},{"contents":"스포츠 유니폼을 일상복처럼 입거나 일상복에 접목한 패션 스타일","retrieved":1706685358346},{"contents":"일본인 가수 ‘쿠보타 토시노부’의 ‘La La La Love Song’. 시티팝 특유의 감성이 그대로 녹아 있는 유명곡 중 하나로 국내에서 많은 아티스트가 커버함","retrieved":1706685358346}]}