{"title":"Careet ─ Contents ─ MZ 용어 사전","url":"https://www.careet.net/Dictionary","favicon":"https://www.careet.net/content/images/favicon.ico","elements":[{"contents":"SNS에서 현재 활동중이라는 뜻.","retrieved":1728731850454},{"contents":"대학내일20대연구소가 정의한 2020 MZ세대 특징 중 하나. MZ세대가 스스로 참여할 수 있는 놀이 ‘판’을 만들어 즐기는 것을 의미함.","retrieved":1728731850459},{"contents":"MZ세대가 최고로 사랑하는 대상, 1순위를 부르는 말.","retrieved":1728731850460},{"contents":"대화 없이 특정 연예인의 짤(이미지)만 공유하는 카카오톡 오픈 채팅방","retrieved":1728731850460},{"contents":"게임적 사고와 게임 기법을 활용해 사용자를 몰입시키는 기법.","retrieved":1728731850460},{"contents":"실제로 알지는 못하지만 온라인 상에서 자주 소식을 접해서 내적으로 친밀감이 쌓였다는 뜻.","retrieved":1728731850460}]}