{"title":"Careet ─ Contents ─ MZ 용어 사전","url":"https://www.careet.net/Dictionary","favicon":"https://www.careet.net/content/images/favicon.ico","elements":[{"title":"발레코어","contents":"발레복에서 파생된 스타일을 부르는 말. 리본 장식이 대표적인 요소.","retrieved":1701040561056},{"title":"스팀","contents":"글로벌 게임 플랫폼.","retrieved":1701040561057},{"title":"언택트","contents":"접촉하다라는 뜻의 '콘택트(contact)'와 부정어 '언(un-)'을 합성한 말.  비대면 방식을 뜻함.","retrieved":1701040561060},{"title":"탭꾸","contents":"태블릿 pc 화면 꾸미기","retrieved":1701040561061},{"title":"퍼블리시티권","contents":"유명인이 자신의 성명이나 초상을 상품 등의 선전에 이용하는 것을 허락하는 권리.","retrieved":1701040561063},{"title":"입틀막","contents":"‘입을 틀어 막다’의 줄임말. 주로 감정이 복받쳐 오를 때 사용함.","retrieved":1701040561064}]}