{"title":"Careet ─ Contents ─ MZ 용어 사전","url":"https://www.careet.net/Dictionary","favicon":"https://www.careet.net/content/images/favicon.ico","elements":[{"title":"단호박","contents":"단호한 사람, 단호한 상황을 일컫는 신조어.","retrieved":1687364501172},{"title":"언박싱","contents":"구매한 물건의 상자를 개봉하는 과정을 담은 유튜브 영상 포맷.","retrieved":1687364501173},{"title":"하울(haul)","contents":"구매한 물건을 보여주면서 품평하는 유튜브 콘텐츠 포맷.","retrieved":1687364501174},{"title":"엄카","contents":"‘엄마 카드’ 등 부모님의 카드를 부르는 말.","retrieved":1687364501174},{"title":"좋댓공","contents":"SNS 게시물에 ‘좋아요’를 누르고, 공유하고, 댓글을 달아 주는 일.","retrieved":1687364501178},{"title":"캐릿 1020 자문단","contents":"10대 50여 명, 20대(27세 이하) 100여 명으로 구성된 캐릿의 트렌드 자문 그룹. MZ세대만 아는 문화, 유행을 발 빠르게 전하는 역할을 맡고 있음.","retrieved":1687364501179}]}