{"title":"Careet ─ Contents ─ MZ 용어 사전","url":"https://www.careet.net/Dictionary","favicon":"https://www.careet.net/content/images/favicon.ico","elements":[{"title":"실트","contents":"트위터 ‘실시간 트렌드’라는 뜻. 현재 얘기가 많이 이루어지는 주제를 트위터 프로그램이 인지해 실시간 트렌드로 올리기 때문에 지금 무엇이 화제인지 알 수 있음.","retrieved":1680074244395},{"title":"차도남","contents":"차가운 도시 남자의 줄임말.","retrieved":1680074244397},{"title":"시강","contents":"‘시선 강탈’의 줄임말. 유독 남들의 시선(이목)을 끄는 것을 의미함.","retrieved":1680074244399},{"title":"홈술","contents":"집에서 술을 마시는 것. 코로나19 이후 증가한 트렌드.","retrieved":1680074244401},{"title":"하지만꽃","contents":"벚꽃을 다르게 부르는 말. '벚꽃 = But꽃 = 하지만꽃'으로 바꿔 부른 카카오톡 짤에서 유래.","retrieved":1680074244404},{"title":"인스","contents":"인쇄 스티커의 줄임말. 인쇄소에 원하는 도안을 보내면 스티커를 소량으로 제작할 수 있음.","retrieved":1680074244407}]}