{"title":"Careet ─ Contents ─ MZ 용어 사전","url":"https://www.careet.net/Dictionary","favicon":"https://www.careet.net/content/images/favicon.ico","elements":[{"title":"엄빠","contents":"엄마 아빠를 함께 일컫는 말.","retrieved":1680995760473},{"title":"뉴노멀(New normal)","contents":"상황 변화에 따라 과거의 표준이 더 이상 통하지 않고 새로운 가치 표준이 세상 변화를 주도하는 상태.","retrieved":1680995760474},{"title":"먼치킨","contents":"비상식적으로 강한 캐릭터를 가르키는 용어. ‘세계관 최강자’와 비슷하게 의미로 사용할 수 있음.","retrieved":1680995760475},{"title":"로판","contents":"로맨스 판타지 장르를 줄여서 부르는 말. 최근 인기있는 웹소설 장르 중 하나.","retrieved":1680995760475},{"title":"공답","contents":"공개 답변의 줄임말. 제품의 정보를 묻고 답할 때 사용함.","retrieved":1680995760476},{"title":"도무송","contents":"칼선이 들어가 모양대로 뗄 수 있는 스티커. 일반적으로 한 장에 스티커 하나씩 들어가 있는 형태가 많음.","retrieved":1680995760477}]}