{"title":"Careet ─ Contents ─ MZ 용어 사전","url":"https://www.careet.net/Dictionary","favicon":"https://www.careet.net/content/images/favicon.ico","elements":[{"title":"어드벤트 캘린더","contents":"12월 1일부터 24일까지 크리스마스를 기다리면서 하나씩 선물을 열어보는 형식의 달력.","retrieved":1686741250787},{"title":"인스타 돋보기","contents":"인스타그램 검색 탭을 일컫는 말. 인스타그램 알고리즘을 이용해 검색바 하단에 추천 콘텐츠를 보여줌. MZ세대가 시간 때울 때 주로 이용하는 기능.","retrieved":1686741250788},{"title":"포카","contents":"포토 카드의 줄임말. 얼굴이 인쇄 된 명함 사이즈의 카드를 의미한다. 요즘 아이돌 앨범에 필수로 들어있는 굿즈임.","retrieved":1686741250789},{"title":"짤털","contents":"‘짤 털기’의 줄임말. 주로 한 주제의 사진 여러 장을 한꺼번에 올리는 일을 부르는 말.","retrieved":1686741250791},{"title":"덕업일치","contents":"덕질하는 것이 직업이 되었다는 뜻. 요즘은 좋아하는 일이 직업이 되었을 때 사용하는 말로 확장됨.","retrieved":1686741250792},{"title":"코덕","contents":"화장품(Cosmetic) 덕후를 부르는 말.","retrieved":1686741250794}]}