{"title":"Careet ─ Contents ─ MZ 용어 사전","url":"https://www.careet.net/Dictionary","favicon":"https://www.careet.net/content/images/favicon.ico","elements":[{"title":"트롤","contents":"온라인에서 사람들의 관심을 끌기 위해 일부러 진행에 방해되는 행동을 하는 것. 또는 그런 사람을 뜻함.","retrieved":1697721666496},{"title":"내수 밈","contents":"온라인에서 널리 쓰이는 밈이 아닌, 특정 트위치 스트리머가 진행하는 방송에서만 사용되는 밈. 마치 내수(국내 수요, Domestic)용 제품처럼 특정한 사람들만 사용하고 외부로 확장되지 않는다는 뜻에서 붙여진 말.","retrieved":1697721666498},{"title":"세포마켓","contents":"1인 미디어 시대에서 SNS를 통해 이뤄지는 1인 마켓. 기업 단위가 아닌 1인 사업자가 주를 이뤄 세포가 분열하는 것처럼 개인 단위로 발전하는 현상을 뜻함.","retrieved":1697721666500},{"title":"쫌쫌따리","contents":"아주 조금씩 틈틈이를 뜻하는 MZ세대 신조어.","retrieved":1697721666502},{"title":"캐릿 1020 해외 특파원","contents":"1020으로 구성된 캐릿의 해외 트렌드 자문 그룹. 해외 각국의 Z세대 트렌드를 발 빠르게 전하는 역할을 맡고 있음.","retrieved":1697721666504},{"title":"포카 슬리브","contents":"포토카드 사이즈로 제작된 얇은 포장용 비닐.","retrieved":1697721666507}]}