{"title":"Careet ─ Contents ─ MZ 용어 사전","url":"https://www.careet.net/Dictionary","favicon":"https://www.careet.net/content/images/favicon.ico","elements":[{"title":"언팔","contents":"‘언팔로우(Unfollow)’의 줄임말. 팔로우를 취소하여 더이상 게시물을 받아보지 않는다는 뜻.","retrieved":1699770010770},{"title":"케미","contents":"서로 간의 궁합이나 호흡을 부르는 데 쓰이는 말. ‘chemistry’에서 유래.","retrieved":1699770010772},{"title":"홈술","contents":"집에서 술을 마시는 것. 코로나19 이후 증가한 트렌드.","retrieved":1699770010774},{"title":"홈트","contents":"‘홈 트레이닝’의 줄임말. 집에서 운동하는 것을 뜻함.","retrieved":1699770010781},{"title":"킹정","contents":"King +‘인정’의 합성어. 강한 인정을 의미함","retrieved":1699770010783},{"title":"사이다 서사","contents":"기승전결을 빠르게 진행하는 서사 전개 형식. 독자가 보기에 답답하거나 전개가 느린 구간이 최소화되었음을 탄산음료의 시원함에 비유한 용어.","retrieved":1699770010785}]}