{"title":"Careet ─ Contents ─ MZ 용어 사전","url":"https://www.careet.net/Dictionary","favicon":"https://www.careet.net/content/images/favicon.ico","elements":[{"title":"인소","contents":"인터넷 소설의 줄임말.","retrieved":1672467682100},{"title":"PTSD","contents":"외상 후 스트레스 장애의 약자. 일상에서는 “과거의 (안 좋은) 경험이 떠올라서 소름 돋는다.”라는 뉘앙스로 활용됨.","retrieved":1672467682103},{"title":"내적 친밀감","contents":"실제로 알지는 못하지만 온라인 상에서 자주 소식을 접해서 내적으로 친밀감이 쌓였다는 뜻.","retrieved":1672467682105},{"title":"밀프렙","contents":"식사(meal)와 준비(preparation)의 합성어. 최대 일주일치 식사를 미리 준비해뒀다가 식사 때마다 먹는 방법.","retrieved":1672467682106},{"title":"안읽씹","contents":"메시지를 읽지도 않고 답장도 하지 않는 경우를 일컫는 표현.","retrieved":1672467682107},{"title":"원툴","contents":"(one tool) 한 가지만 잘 한다는 말.","retrieved":1672467682112}]}