{"title":"Careet ─ Contents ─ MZ 용어 사전","url":"https://www.careet.net/Dictionary","favicon":"https://www.careet.net/content/images/favicon.ico","elements":[{"contents":"‘어차피 덕질할 거 행복하게 덕질하자.’를 줄여 이르는 말.","retrieved":1708179294096},{"contents":"'기분 좋은 소름'을 뜻하는 ASMR 용어.","retrieved":1708179294097},{"contents":"'잘 안다', '잘 아는 사람'이라는 뜻의 신조어.","retrieved":1708179294098},{"contents":"무언가를 소비하고 싶은 충동을 부르는 온라인 유행어.","retrieved":1708179294099},{"contents":"인스타 스토리를 프로필란에 고정할 수 있는 기능.","retrieved":1708179294099},{"contents":"실제론 친환경이 아닌데 친환경인 척 광고하는 것.","retrieved":1708179294101}]}