{"title":"Careet ─ Contents ─ MZ 용어 사전","url":"https://www.careet.net/Dictionary","favicon":"https://www.careet.net/content/images/favicon.ico","elements":[{"title":"래플","contents":"당첨자에게 한정판 상품을 구매할 권리를 주는 판매 방식. 이 방식을 활용하는 브랜드로는 대표적으로 나이키가 있음.","retrieved":1692493757526},{"title":"밸붕","contents":"밸런스 붕괴, 특정 아이템의 성능이 매우 출중하여 다른 아이템과 공정한 비교가 어려울 때 쓰는 말. 주로 게임 용어로 쓰였으나 요즘에는 다양한 분야에서 활용됨.","retrieved":1692493757529},{"title":"코덕","contents":"화장품(Cosmetic) 덕후를 부르는 말.","retrieved":1692493757533},{"title":"국룰","contents":"국민 룰의 줄임말. 보편적으로 통용되는 규칙 혹은 유행이라는 뜻.","retrieved":1692493757535},{"title":"킬포","contents":"‘킬링 포인트’의 줄임말. ‘하이라이트’와 비슷한 의미로 사용됨.","retrieved":1692493757537},{"title":"킹정","contents":"King +‘인정’의 합성어. 강한 인정을 의미함","retrieved":1692493757540}]}