{"title":"Careet ─ Contents ─ MZ 용어 사전","url":"https://www.careet.net/Dictionary","favicon":"https://www.careet.net/content/images/favicon.ico","elements":[{"title":"학예사","contents":"박물관, 미술관 등에서 작품 등을 수집, 전시 기획 등을 하는 전문 직업.","retrieved":1701760550642},{"title":"시즈니","contents":"SM엔터테인먼트 보이그룹 NCT의 팬 ncitizen의 애칭.","retrieved":1701760550643},{"title":"세포마켓","contents":"1인 미디어 시대에서 SNS를 통해 이뤄지는 1인 마켓. 기업 단위가 아닌 1인 사업자가 주를 이뤄 세포가 분열하는 것처럼 개인 단위로 발전하는 현상을 뜻함.","retrieved":1701760550647},{"title":"짠메랑","contents":"‘부메랑(gif 형식으로 사진을 찍어주는 필터)’기능을 활용해 술자리에서 건배하는 모습을 촬영하는 것.","retrieved":1701760550649},{"title":"굿즈","contents":"원래 연예인과 관련된 사진, 포토카드, 응원봉 등의 제품을 뜻했으나, 최근엔 ‘한정판으로 출시되는 매력적인 아이템’을 통칭하는 단어로 자리잡음.","retrieved":1701760550650},{"title":"파이프라인","contents":"돈이 들어오는 시스템, 수입원.","retrieved":1701760550652}]}