{"title":"Careet ─ Contents ─ MZ 용어 사전","url":"https://www.careet.net/Dictionary","favicon":"https://www.careet.net/content/images/favicon.ico","elements":[{"title":"임플로이언서","contents":"Employee+Influencer. 직원으로서 기업의 브랜딩과 이미지에 영향력을 미치는 존재.","retrieved":1662276024056},{"title":"인쇼","contents":"‘인터넷 쇼핑’의 줄임말.","retrieved":1662276024057},{"title":"하이라이트","contents":"인스타 스토리를 프로필란에 고정할 수 있는 기능.","retrieved":1662276024058},{"title":"학예사","contents":"박물관, 미술관 등에서 작품 등을 수집, 전시 기획 등을 하는 전문 직업.","retrieved":1662276024059},{"title":"하울(haul)","contents":"구매한 물건을 보여주면서 품평하는 유튜브 콘텐츠 포맷.","retrieved":1662276024060},{"title":"디지털 굿즈","contents":"휴대폰·아이패드 배경화면, 카카오톡 테마 등 모바일 환경에 적용해서 사용할 수 있는 템플릿. 실물 굿즈가 아닌 온라인에서 배포할 수 있다는 점이 특징.","retrieved":1662276024061}]}