{"title":"Careet ─ Contents ─ MZ 용어 사전","url":"https://www.careet.net/Dictionary","favicon":"https://www.careet.net/content/images/favicon.ico","elements":[{"title":"마테","contents":"마스킹테이프의 준말. 주로 다이어리 등을 꾸밀 때 이용됨","retrieved":1655324536728},{"title":"캐릿 1020 자문단","contents":"10대 50여 명, 20대(27세 이하) 100여 명으로 구성된 캐릿의 트렌드 자문 그룹. MZ세대만 아는 문화, 유행을 발 빠르게 전하는 역할을 맡고 있음.","retrieved":1655324536729},{"title":"처돌이","contents":"치킨 브랜드 ‘처갓집’의 마스코트 ‘처돌이’에서 유래한 말. 특정 대상을 매우 좋아한다는 뜻.","retrieved":1655324536731},{"title":"준등기깡","contents":"준등기로 배송된 우편물을 뜯어보는 것. 10~20대는 포토 카드 등 소형 굿즈를 준등기로 거래하는 경우가 많아 생긴 신조어.","retrieved":1655324536732},{"title":"스불재","contents":"‘스스로 불러온 재앙에 짓눌려’의 준말. 노래 Lazenca, save us에서 탄생한 밈.","retrieved":1655324536733},{"title":"웃수저","contents":"‘금수저’를 응용한 신조어로, 딱히 노력하지 않아도 주변 사람들에게 웃음을 주는 재능을 가진 사람을 뜻하는 말.","retrieved":1655324536735}]}