{"title":"Careet ─ Contents ─ MZ 용어 사전","url":"https://www.careet.net/Dictionary","favicon":"https://www.careet.net/content/images/favicon.ico","elements":[{"title":"마스킹 테이프","contents":"손으로 찢어 사용할 수 있는 종이 테이프. 다양한 디자인으로, 다이어리를 꾸미는 MZ세대에게 필수템으로 통함.","retrieved":1691684489882},{"title":"레딧","contents":"미국에서 만들어진 커뮤니티 사이트로 해외 MZ세대가 즐겨찾음. 주제별 게시판인 ‘서브레딧’이 따로 있는 것이 특징.","retrieved":1691684489883},{"title":"디깅","contents":"digging, 한글로 직역하면 ‘발굴’이라는 뜻. MZ세대 사이에선 흥미 있는 분야의 정보를 얻기 위해 이것저것 검색해보는 일을 의미함.","retrieved":1691684489885},{"title":"앱테크","contents":"앱+재테크의 합성어. 앱 안에서 특정 활동을 해 포인트를 쌓는 것","retrieved":1691684489887},{"title":"씽크빅","contents":"학습지 이름 ‘씽크빅’에서 유래한 표현. 창의력이 뛰어난 대상을 칭찬할 때 쓰인다. “어릴 때 씽크빅 좀 했나 봐?”라는 문장에서 파생돼 “오, 씽크빅!”같은 감탄사로도 쓰임.","retrieved":1691684489888},{"title":"서사","contents":"어떤 인물에게 부여된 스토리.","retrieved":1691684489890}]}