{"title":"Careet ─ Contents ─ MZ 용어 사전","url":"https://www.careet.net/Dictionary","favicon":"https://www.careet.net/content/images/favicon.ico","elements":[{"title":"버블","contents":"스타와 마치 1:1 메시지를 주고받는 것처럼 소통할 수 있게 만들어진 프라이빗 메시지 앱. 유료로 이용이 가능하며 아이돌 팬덤이 활발하게 이용하는 서비스로 유명함.","retrieved":1655742776976},{"title":"초멘","contents":"안면이 없다는 뜻의 ‘초면’과 ‘멘션을 합친 트위터 용어.","retrieved":1655742776977},{"title":"드래곤볼","contents":"MZ세대는 무언가를 모을 때 ‘드래곤볼’이라고 표현함. 만화 &lt;드래곤볼&gt;의 내용이 구슬 일곱개를 모아야 한다는 점에서 유래됨.","retrieved":1655742776978},{"title":"미라클 모닝","contents":"4시 30분, 6시 등 새벽에 일어나 하루를 시작하는 생활 방식. 미라클 모닝을 실천하는 유튜버들의 영향이 크며, Z세대의 갓생 트렌드와 연관이 깊음.","retrieved":1655742776979},{"title":"현활","contents":"SNS에서 현재 활동중이라는 뜻.","retrieved":1655742776980},{"title":"드볼","contents":"포카, 스티커 등 여러 종으로 나온 굿즈를 모두 모으는 것을 만화 &lt;드래곤 볼&gt;에 빗대어 부르는 말.","retrieved":1655742776982}]}