{"title":"Careet ─ Contents ─ MZ 용어 사전","url":"https://www.careet.net/Dictionary","favicon":"https://www.careet.net/content/images/favicon.ico","elements":[{"title":"앨범깡","contents":"앨범 언박싱을 부르는 말. 주로 원하는 포토카드를 얻기 위해 연속해서 앨범을 열어보는 것을 말함.","retrieved":1670872704729},{"title":"뇌절","contents":"똑같은 말이나 행동을 반복해 상대를 질리게 하는 것을 지칭.","retrieved":1670872704731},{"title":"랩핑지","contents":"A4~A5의 사이즈의 배경지. 주로 포장이나 꾸미기에 활용되고 있음.","retrieved":1670872704733},{"title":"깡","contents":"덕질 용어에서 처음 시작된 단어로 깡은 깐다의 줄임말. 원하는 제품을 깐다는 말로 해석할 수 있다. 비슷한 단어로는 언박싱이 있다.","retrieved":1670872704736},{"title":"솜뭉치","contents":"MZ세대가 ‘인형’을 부르는 애칭.","retrieved":1670872704737},{"title":"알못","contents":"어떤 분야에 대해 잘 알지 못하는 사람을 부르는 말↔잘알","retrieved":1670872704739}]}