{"title":"Careet ─ Contents ─ MZ 용어 사전","url":"https://www.careet.net/Dictionary","favicon":"https://www.careet.net/content/images/favicon.ico","elements":[{"contents":"‘내 돈으로 내가 산’의 줄임말. 주로 제품 리뷰를 할 때 광고가 아니라는 것을 강조하기 위해 사용함.","retrieved":1724577581328},{"contents":"god(신)과 인생이 합쳐진 단어로, 부지런하고 알찬 삶을 사는 것을 일컫는 말.","retrieved":1724577581329},{"contents":"알파 세대 유행어. ‘어쩌라고, TV나 봐’라는 의미로 추정됨.","retrieved":1724577581331},{"contents":"‘신발 꾸미기’의 줄임말.","retrieved":1724577581332},{"contents":"‘빛의 속도로 삭제한다’의 줄임말로 인터넷상에 올린 게시물을 매우 빠르게 지운다는 의미.","retrieved":1724577581333},{"contents":"‘답은 정해져 있고 너는 대답만 하면 돼’의 줄임말.","retrieved":1724577581334}]}