{"title":"Careet ─ Contents ─ MZ 용어 사전","url":"https://www.careet.net/Dictionary","favicon":"https://www.careet.net/content/images/favicon.ico","elements":[{"title":"취준","contents":"‘취업 준비’의 줄임말.","retrieved":1654605684011},{"title":"크루얼티 프리","contents":"‘학대(cruelty)가 없다(free)’는 의미로, 동물 실험을 하지 않거나 동물 유래 원료를 사용하지 않은 제품을 뜻함.","retrieved":1654605684012},{"title":"ㅈㅂㅈㅇ","contents":"정보좀요의 초성을 따서 만든 MZ세대 신조어. 패션 앱 스타일쉐어에서 상대방에게 제품 정보를 물어볼 때 사용했던 것에서 유래함.","retrieved":1654605684015},{"title":"와드","contents":"관심 있는 정보의 업데이트 내용을 실시간으로 확인하기 위해서 댓글을 남겨두는 행위.","retrieved":1654605684016},{"title":"PTSD","contents":"외상 후 스트레스 장애의 약자. 일상에서는 “과거의 (안 좋은) 경험이 떠올라서 소름 돋는다.”라는 뉘앙스로 활용됨.","retrieved":1654605684017},{"title":"OO깡","contents":"덕질 용어에서 처음 시작된 단어로 깡은 깐다의 줄임말. 원하는 제품을 깐다는 말로 해석할 수 있다. 비슷한 단어로는 언박싱이 있다.","retrieved":1654605684021}]}