{"title":"Careet ─ Contents ─ MZ 용어 사전","url":"https://www.careet.net/Dictionary","favicon":"https://www.careet.net/content/images/favicon.ico","elements":[{"title":"PTSD","contents":"외상 후 스트레스 장애의 약자. 일상에서는 “과거의 (안 좋은) 경험이 떠올라서 소름 돋는다.”라는 뉘앙스로 활용됨.","retrieved":1695932172141},{"title":"어사","contents":"어색한 사이의 줄임말↔찐친","retrieved":1695932172142},{"title":"캐해석","contents":"캐릭터 해석의 줄임말. 특정 인물을 분석해 나름의 이미지를 설정하는 일을 의미함.","retrieved":1695932172145},{"title":"맛도리","contents":"‘맛있는 음식’이라는 뜻의 온라인 신조어.","retrieved":1695932172146},{"title":"플미","contents":"‘프리미엄’의 줄임말. 주로 희소성있는 제품이 판매가보다 비싸게 거래될 때 ‘플미붙었다’고 표현함.","retrieved":1695932172148},{"title":"네카라쿠배당토","contents":"네이버, 카카오, 라인, 배달의민족, 당근마켓, 토스 등 신흥 IT 기업을 통칭하는 말. MZ세대 취업 준비생들이 입사하고 싶어하는 꿈의 직장으로 떠오르는 기업들.","retrieved":1695932172150}]}