{"title":"Careet ─ Contents ─ MZ 용어 사전","url":"https://www.careet.net/Dictionary","favicon":"https://www.careet.net/content/images/favicon.ico","elements":[{"contents":"어떤 인물에게 부여된 스토리.","retrieved":1720120548243},{"contents":"배트 플립(bat flip)의 한국식 표기. 일명 ‘빠따 던지기’의 줄임말. 타자가 홈런이 짐작되는 타격을 한 뒤, 야구 방망이를 던지는 행위를 말함.","retrieved":1720120548244},{"contents":"바이트댄스에서 2016년 출시한 숏폼 서비스.","retrieved":1720120548245},{"contents":"'기분 좋은 소름'을 뜻하는 ASMR 용어.","retrieved":1720120548246},{"contents":"혼자 활동을 즐기는 사람을 부르는 말. 주로 게임과 관련해서 쓰임.","retrieved":1720120548247},{"contents":"연예인이 자신의 팬들에게 선물을 주는 행동 혹은 그 선물을 가르키는 말.","retrieved":1720120548248}]}