{"title":"Careet ─ Contents ─ MZ 용어 사전","url":"https://www.careet.net/Dictionary","favicon":"https://www.careet.net/content/images/favicon.ico","elements":[{"title":"사바사","contents":"‘사람 by 사람’의 줄임말. 사람마다 다 다르다는 것을 의미함.","retrieved":1679825861476},{"title":"알파 세대","contents":"2010년 이후 출생자, 즉 Z세대 이후 세대를 부르는 말.","retrieved":1679825861478},{"title":"쫌쫌따리","contents":"아주 조금씩 틈틈이를 뜻하는 MZ세대 신조어.","retrieved":1679825861480},{"title":"사이다 서사","contents":"기승전결을 빠르게 진행하는 서사 전개 형식. 독자가 보기에 답답하거나 전개가 느린 구간이 최소화되었음을 탄산음료의 시원함에 비유한 용어.","retrieved":1679825861482},{"title":"라방","contents":"라이브 방송의 줄임말.","retrieved":1679825861484},{"title":"어사","contents":"어색한 사이의 줄임말↔찐친","retrieved":1679825861485}]}