{"title":"Careet ─ Contents ─ MZ 용어 사전","url":"https://www.careet.net/Dictionary","favicon":"https://www.careet.net/content/images/favicon.ico","elements":[{"title":"액괴","contents":"액체 괴물의 줄임말. 알파 세대에게 인기 있는 장난감인 ‘슬라임’을 지칭하는 용어이다.","retrieved":1689758229922},{"title":"초멘","contents":"안면이 없다는 뜻의 ‘초면’과 ‘멘션을 합친 트위터 용어.","retrieved":1689758229923},{"title":"블챌","contents":"‘블로그 챌린지’의 줄임말. 6월부터 12월까지 6개월간 진행되는 장기 프로젝트로 매주 지정된 카테고리에 한 건 이상의 일기를 작성해야 챌린지를 이어갈 수 있음.","retrieved":1689758229923},{"title":"비건","contents":"원래는 채식주의 중에서도 가장 엄격한 단계를 뜻하는 단어지만, 요즘은 철학적인 이유로 동물성 식품을 섭취하지 않는 사람들을 통칭해 ‘비건’이라고 부르는 경우가 많음.","retrieved":1689758229927},{"title":"카공","contents":"카페에서 공부하는 것의 줄임말.","retrieved":1689758229928},{"title":"어사","contents":"어색한 사이의 줄임말↔찐친","retrieved":1689758229930}]}